pyzample/__init__.py
pyzample-1.0.0.dist-info/WHEEL
pyzample-1.0.0.dist-info/METADATA
pyzample-1.0.0.dist-info/RECORD
