Metadata-Version: 2.1
Name: pyzample
Version: 1.0.0
Summary: Tests and Documentation Done by Example. An alias for the project `examples` with better SEO opportunities
License: MIT
Author: Timothy Crosley
Author-email: timothy.crosley@gmail.com
Requires-Python: >=3.6,<4.0
Classifier: License :: OSI Approved :: MIT License
Classifier: Programming Language :: Python :: 3
Classifier: Programming Language :: Python :: 3.6
Classifier: Programming Language :: Python :: 3.7
Requires-Dist: examples (>=0.0.2,<0.0.3)
